{"id":"style.scss","dependencies":[{"name":"D:\\Project\\home\\package.json","includedInParent":true,"mtime":1537001192468},{"name":"D:/Project/home/_variable.scss","includedInParent":true,"mtime":1537003016544},{"name":"_css_loader","parent":"D:\\Project\\home\\style.scss","resolved":"C:\\Users\\Admin\\AppData\\Roaming\\npm\\node_modules\\parcel-bundler\\src\\builtins\\css-loader.js"}],"generated":{"css":"html,\nbody {\n  width: 100%;\n  margin: 0;\n  padding: 0;\n  position: relative;\n  background: #000; }\n\n@keyframes animateLogo {\n  0% {\n    right: 0%; }\n  100% {\n    right: -400%; } }\n\n@keyframes animateScrollDown {\n  0% {\n    transform: translate(-50%, 5px);\n    opacity: 0; }\n  80% {\n    transform: translate(-50%, 10px);\n    opacity: 1; }\n  100% {\n    transform: translate(-50%, 20px);\n    opacity: 0; } }\n\n.logo {\n  position: fixed;\n  top: 0;\n  left: 10px; }\n  .logo svg {\n    width: 100px;\n    height: 60px; }\n\n.reloader {\n  position: fixed;\n  overflow: hidden;\n  height: 100vh;\n  width: 100%;\n  transition: 1s;\n  z-index: 4;\n  background-color: #000;\n  overflow: hidden; }\n  .reloader .loader {\n    position: absolute;\n    top: 50%;\n    left: 50%;\n    transform: translate(-50%, -50%); }\n  .reloader:after {\n    content: '';\n    position: absolute;\n    top: 0;\n    right: 0;\n    width: 400%;\n    height: 100%;\n    background: linear-gradient(to right, transparent, #000, #000);\n    animation: animateLogo 2s linear forwards; }\n  .reloader svg {\n    width: 30vw; }\n  .reloader h3 {\n    width: 30vw;\n    color: #fff;\n    text-align: center;\n    width: 100%;\n    font-size: 34px;\n    font-family: Arial, 'Helvetica Neue', Helvetica, sans-serif;\n    letter-spacing: 10px;\n    margin-top: -35px; }\n\n.button-open-navigation {\n  cursor: pointer;\n  background-color: #f12711;\n  position: fixed;\n  border-radius: 50%;\n  top: 50%;\n  transform: translate(0, -50%);\n  right: -30px;\n  width: 70px;\n  height: 70px;\n  z-index: 3; }\n  .button-open-navigation i {\n    position: absolute;\n    top: 48%;\n    font-size: 22px;\n    left: 23%;\n    transform: translate(0, -50%); }\n\n.navigation {\n  position: fixed;\n  width: 500px;\n  border-radius: 50%;\n  height: 100vh;\n  right: -500px;\n  background: #f12711;\n  z-index: 3; }\n  .navigation .button {\n    position: absolute;\n    top: 30%;\n    left: 20%;\n    transform: translate(0, -50%);\n    overflow: hidden;\n    width: 30px;\n    height: 30px;\n    cursor: pointer;\n    transition: 0.5s; }\n    .navigation .button i {\n      width: 100%;\n      height: 100%;\n      transition: 0.5s;\n      font-size: 24px; }\n  .navigation ul {\n    position: absolute;\n    right: 250px;\n    top: 50%;\n    transform: translate(0, -50%); }\n    .navigation ul li {\n      list-style: none;\n      width: 50px;\n      margin: 15px 0; }\n      .navigation ul li a {\n        color: #fff;\n        text-decoration: none;\n        position: relative; }\n        .navigation ul li a:hover .icon i, .navigation ul li a.active .icon i {\n          transform: translateY(-100%); }\n        .navigation ul li a:hover .name span, .navigation ul li a.active .name span {\n          transform: translateY(100%); }\n        .navigation ul li a .icon {\n          color: #fff;\n          font-size: 30px;\n          height: 45px;\n          width: 45px;\n          line-height: 45px;\n          align-content: center;\n          transition: 0.5s;\n          overflow: hidden; }\n          .navigation ul li a .icon i {\n            transition: 0.5s;\n            width: 100%;\n            height: 100%;\n            line-height: 45px; }\n            .navigation ul li a .icon i:last-child {\n              color: #000; }\n        .navigation ul li a .name {\n          position: absolute;\n          font-size: 15px;\n          top: -27px;\n          right: 20px;\n          overflow: hidden;\n          text-transform: uppercase;\n          font-weight: 700;\n          font-family: Arial, 'Helvetica Neue', Helvetica, sans-serif; }\n          .navigation ul li a .name span {\n            display: block;\n            position: relative;\n            color: #fff;\n            width: 100%;\n            transition: 0.5s; }\n            .navigation ul li a .name span:before {\n              content: attr(data-text);\n              color: #000;\n              position: absolute;\n              top: -100%;\n              width: 100%;\n              height: 100%; }\n\n.home {\n  height: 100vh;\n  color: #fff;\n  overflow: hidden; }\n  .home .video {\n    position: relative;\n    z-index: 1;\n    overflow: hidden; }\n    .home .video:before {\n      content: '';\n      position: absolute;\n      bottom: 0;\n      left: 0;\n      width: 100vw;\n      height: 100vh;\n      background: linear-gradient(to right, #000000, black, rgba(0, 0, 0, 0.8)); }\n    .home .video video {\n      z-index: -1;\n      top: 0;\n      left: 0;\n      width: 100%;\n      height: 100vh; }\n  .home .scroll-down {\n    position: absolute;\n    bottom: 0;\n    left: 50%;\n    transform: translate(0, -50%);\n    z-index: 3; }\n    .home .scroll-down .mouse {\n      position: relative;\n      width: 20px;\n      height: 30px;\n      border-radius: 25px;\n      background: transparent;\n      border: 2px solid #f12711; }\n      .home .scroll-down .mouse:before {\n        content: '';\n        position: absolute;\n        width: 4px;\n        height: 2px;\n        border-radius: 50%;\n        background-color: #f12711;\n        left: 50%;\n        top: 5px;\n        transform: translate(-50%, 0);\n        animation: animateScrollDown 1s linear infinite; }\n      .home .scroll-down .mouse:after {\n        content: '';\n        position: absolute;\n        width: 2px;\n        height: 5px;\n        background-color: #f12711;\n        left: 50%;\n        top: 5px;\n        transform: translate(-50%, 0); }\n","js":"\nvar reloadCSS = require('_css_loader');\nmodule.hot.dispose(reloadCSS);\nmodule.hot.accept(reloadCSS);"},"hash":"61a2b773e118a2bae64b4ff4eab3593c","cacheData":{"env":{}}}